rten_convert/__init__.py
rten_convert/attr_reader.py
rten_convert/converter.py
rten_convert/errors.py
rten_convert/graph.py
rten_convert/schema_generated.py
rten_convert/tensor_data.py
rten_convert/util.py
rten_convert-0.22.0.dist-info/licenses/LICENSE
rten_convert-0.22.0.dist-info/METADATA
rten_convert-0.22.0.dist-info/WHEEL
rten_convert-0.22.0.dist-info/entry_points.txt
rten_convert-0.22.0.dist-info/top_level.txt
rten_convert-0.22.0.dist-info/RECORD
