Metadata-Version: 2.4
Name: rten-convert
Version: 0.22.0
Summary: Convert ONNX models to .rten format
Project-URL: Homepage, https://github.com/robertknight/rten
Project-URL: Issues, https://github.com/robertknight/rten/issues
Classifier: License :: OSI Approved :: MIT License
Requires-Python: >=3.10
License-File: LICENSE
Requires-Dist: flatbuffers
Requires-Dist: onnx
Requires-Dist: numpy
Dynamic: license-file
